karthi_package/__init__.py
karthi_package/operation.py
karthi_package/utils.py
karthi_package-0.2.dist-info/METADATA
karthi_package-0.2.dist-info/WHEEL
karthi_package-0.2.dist-info/top_level.txt
karthi_package-0.2.dist-info/RECORD
