Metadata-Version: 2.2
Name: karthi_package
Version: 0.2
Summary: A package for numerical operations using NumPy
Author: karthi
Author-email: karthi@gmail.com
Requires-Dist: numpy>=1.21.0
Dynamic: author
Dynamic: author-email
Dynamic: requires-dist
Dynamic: summary
